secwebapi/__init__.py
secwebapi-2024.10.1.dist-info/METADATA
secwebapi-2024.10.1.dist-info/WHEEL
secwebapi-2024.10.1.dist-info/top_level.txt
secwebapi-2024.10.1.dist-info/RECORD
