Metadata-Version: 2.2
Name: secwebapi
Version: 2024.10.1
Summary: A Python package to interact with the Secwe API
Home-page: https://secwe.pythonanywhere.com
Author: Samet Azaboglu
Author-email: sametazaboglu@gmail.com
Requires-Dist: requests
Requires-Dist: tldextract
Requires-Dist: aiohttp
Dynamic: author
Dynamic: author-email
Dynamic: description
Dynamic: description-content-type
Dynamic: home-page
Dynamic: requires-dist
Dynamic: summary
